nirwals/__init__.py
nirwals/edge_subtract.py
nirwals/nirwals.py
nirwals/nirwals_explorer.py
nirwals/nirwals_fit_nonlinearity.py
nirwals/nirwals_reduce.py
nirwals/nirwals_urg_algorithms.py
nirwals/nirwals_watchdog.py
nirwals/plotcube.py
nirwals/previous_file_picker.py
nirwals/provenance.py
nirwals/refpixel_calibrate.py
nirwals/single_pixel_check.py
nirwals/data/__init__.py
nirwals/data/fiber_map_20221018.csv
nirwals/data/fibermap.py
nirwals/data/gain.py
nirwals-0.1.7.dist-info/LICENSE.rst
nirwals-0.1.7.dist-info/METADATA
nirwals-0.1.7.dist-info/WHEEL
nirwals-0.1.7.dist-info/entry_points.txt
nirwals-0.1.7.dist-info/top_level.txt
nirwals-0.1.7.dist-info/RECORD
