Metadata-Version: 2.1
Name: nirwals
Version: 0.1.7
Summary: basic instrument signature removal for the NIRWALS instrument on the SALT telescope
Author-email: Ralf Kotulla <ralf.kotulla@gmail.com>
License: BSD-3-Clause
Project-URL: Homepage, https://github.com/SALT-NIRWALS/nirwals
Project-URL: Bug Tracker, https://github.com/SALT-NIRWALS/nirwals/issues
Classifier: Programming Language :: Python :: 3
Classifier: License :: OSI Approved :: MIT License
Classifier: Operating System :: OS Independent
Requires-Python: >=3.8
License-File: LICENSE.rst
Requires-Dist: astropy
Requires-Dist: matplotlib
Requires-Dist: multiparlog ==1.0.9
Requires-Dist: numpy
Requires-Dist: pandas
Requires-Dist: scipy
Requires-Dist: scikit-learn
Requires-Dist: pyvo
Requires-Dist: watchdog
Requires-Dist: sysv-ipc
